XmlFraction/__init__.py
XmlFraction/__main__.py
XmlFraction-2024.14.9a1.dist-info/METADATA
XmlFraction-2024.14.9a1.dist-info/WHEEL
XmlFraction-2024.14.9a1.dist-info/top_level.txt
XmlFraction-2024.14.9a1.dist-info/RECORD
