Metadata-Version: 2.1
Name: XmlFraction
Version: 2024.14.9a1
Summary: Best Fractional Library!!!
